Mopidy_Local_SQLite-1.0.0.dist-info/METADATA
Mopidy_Local_SQLite-1.0.0.dist-info/WHEEL
Mopidy_Local_SQLite-1.0.0.dist-info/entry_points.txt
Mopidy_Local_SQLite-1.0.0.dist-info/DESCRIPTION.rst
Mopidy_Local_SQLite-1.0.0.dist-info/top_level.txt
Mopidy_Local_SQLite-1.0.0.dist-info/metadata.json
Mopidy_Local_SQLite-1.0.0.dist-info/RECORD
mopidy_local_sqlite/ext.conf
mopidy_local_sqlite/schema.py
mopidy_local_sqlite/library.py
mopidy_local_sqlite/__init__.py
mopidy_local_sqlite/sql/upgrade-v1.sql
mopidy_local_sqlite/sql/schema.sql
mopidy_local_sqlite/sql/upgrade-v3.sql
mopidy_local_sqlite/sql/upgrade-v2.sql
mopidy_local_sqlite/sql/upgrade-v4.sql
mopidy_local_sqlite/sql/upgrade-v5.sql
