Metadata-Version: 2.0
Name: Mopidy-Local-SQLite
Version: 1.0.0
Summary: Mopidy SQLite local library extension
Home-page: https://github.com/mopidy/mopidy-local-sqlite
Author: Thomas Kemmer
Author-email: tkemmer@computer.org
License: Apache License, Version 2.0
Platform: UNKNOWN
Classifier: Environment :: No Input/Output (Daemon)
Classifier: Intended Audience :: End Users/Desktop
Classifier: License :: OSI Approved :: Apache Software License
Classifier: Operating System :: OS Independent
Classifier: Programming Language :: Python :: 2
Classifier: Topic :: Multimedia :: Sound/Audio :: Players
Requires-Dist: setuptools
Requires-Dist: Mopidy (>=1.1)
Requires-Dist: Pykka (>=1.1)
Requires-Dist: uritools (>=1.0)
